artbot/__init__.py
artbot/__main__.py
artbot/api.py
artbot/fetch_images.py
artbot/pixel_to_ascii.py
artbot_philippe_noa-0.2.4.dist-info/METADATA
artbot_philippe_noa-0.2.4.dist-info/WHEEL
artbot_philippe_noa-0.2.4.dist-info/entry_points.txt
artbot_philippe_noa-0.2.4.dist-info/top_level.txt
artbot_philippe_noa-0.2.4.dist-info/RECORD
