Metadata-Version: 2.4
Name: artbot_Philippe_Noa
Version: 0.2.4
Summary: Un convertisseur d'images vers ASCII à partir d'URLs Unsplash
Author: GambeyNoa/MathieuPhilippe
Classifier: Programming Language :: Python :: 3
Classifier: License :: OSI Approved :: MIT License
Requires-Python: >=3.8
Requires-Dist: fastapi
Requires-Dist: uvicorn
Requires-Dist: requests
Requires-Dist: beautifulsoup4
Requires-Dist: pillow
Dynamic: author
Dynamic: classifier
Dynamic: description
Dynamic: description-content-type
Dynamic: requires-dist
Dynamic: requires-python
Dynamic: summary
